colorado/__init__.py
colorado/win32.py
colorado/winterm.py
colorado-1.1.dist-info/LICENSE.txt
colorado-1.1.dist-info/METADATA
colorado-1.1.dist-info/WHEEL
colorado-1.1.dist-info/top_level.txt
colorado-1.1.dist-info/RECORD
