Metadata-Version: 2.1
Name: colorado
Version: 1.1
Summary: Games 2D
Author: Lauren Jackson
Author-email: laurendevyork@gmail.com
Classifier: Programming Language :: Python :: 3
Classifier: License :: OSI Approved :: MIT License
Classifier: Operating System :: OS Independent
License-File: LICENSE.txt
